pytest_iters/__init__.py
pytest_iters/py.typed
pytest_iters-0.0.3.dist-info/METADATA
pytest_iters-0.0.3.dist-info/WHEEL
pytest_iters-0.0.3.dist-info/entry_points.txt
pytest_iters-0.0.3.dist-info/namespace_packages.txt
pytest_iters-0.0.3.dist-info/top_level.txt
pytest_iters-0.0.3.dist-info/RECORD
